FirstBS/__init__.py
FirstBS/module_conclient.py
FirstBS/server.py
FirstBS_pkg-0.0.1.dist-info/LICENSE
FirstBS_pkg-0.0.1.dist-info/METADATA
FirstBS_pkg-0.0.1.dist-info/WHEEL
FirstBS_pkg-0.0.1.dist-info/top_level.txt
FirstBS_pkg-0.0.1.dist-info/RECORD
