Metadata-Version: 2.1
Name: FirstBS-pkg
Version: 0.0.1
Summary: Simple Keylogger Program
Home-page: UNKNOWN
Author: BS
Author-email: qudtnwkdrns1@naver.com
License: UNKNOWN
Platform: UNKNOWN
License-File: LICENSE
